Math_Module/__init__.py
Math_Module/main_file.py
Math_Module/mult_file.py
Math_Module/First_module/__init__.py
Math_Module/First_module/add_file.py
Math_Module/First_module/sub_file.py
python_practice-0.0.1.dist-info/METADATA
python_practice-0.0.1.dist-info/WHEEL
python_practice-0.0.1.dist-info/top_level.txt
python_practice-0.0.1.dist-info/RECORD
